simple_acp_client/__init__.py
simple_acp_client/core.py
simple_acp_client/capabilities/__init__.py
simple_acp_client/capabilities/filesystem.py
simple_acp_client/capabilities/terminal.py
simple_acp_client/sdk/__init__.py
simple_acp_client/sdk/client.py
simple_acp_client-0.1.6.dist-info/licenses/LICENSE
simple_acp_client-0.1.6.dist-info/METADATA
simple_acp_client-0.1.6.dist-info/WHEEL
simple_acp_client-0.1.6.dist-info/top_level.txt
simple_acp_client-0.1.6.dist-info/RECORD
