Metadata-Version: 2.4
Name: simple-acp-client
Version: 0.1.6
Summary: Python SDK for the Agent Client Protocol (ACP) - Build powerful agent-based applications with streaming, terminal, and filesystem capabilities
Keywords: acp,agent,protocol,sdk,async,streaming,ai
Classifier: Development Status :: 3 - Alpha
Classifier: Intended Audience :: Developers
Classifier: Programming Language :: Python :: 3
Classifier: Programming Language :: Python :: 3.11
Classifier: Programming Language :: Python :: 3.12
Classifier: License :: OSI Approved :: MIT License
Classifier: Operating System :: OS Independent
Classifier: Topic :: Software Development :: Libraries :: Python Modules
Classifier: Framework :: AsyncIO
Requires-Python: >=3.11
License-File: LICENSE
Requires-Dist: agent-client-protocol==0.6.3
Requires-Dist: fastmcp>=2.13.1
Dynamic: license-file
